puretalk/__init__.py
puretalk/main.py
puretalk/model/__pycache__/data_loader.cpython-310.pyc
puretalk/model/__pycache__/tts.cpython-310.pyc
puretalk/model/__pycache__/utils.cpython-310.pyc
puretalk/model/config.py
puretalk/model/data_loader.py
puretalk/model/inference.py
puretalk/model/trainer.py
puretalk/model/tts.py
puretalk/model/utils.py
puretalk/utils.py
puretalk-0.1.2.dist-info/METADATA
puretalk-0.1.2.dist-info/WHEEL
puretalk-0.1.2.dist-info/entry_points.txt
puretalk-0.1.2.dist-info/RECORD
